zdbpydra/__init__.py
zdbpydra/__main__.py
zdbpydra/client.py
zdbpydra/docs.py
zdbpydra/utils.py
zdbpydra-0.3.4.dist-info/LICENSE
zdbpydra-0.3.4.dist-info/METADATA
zdbpydra-0.3.4.dist-info/WHEEL
zdbpydra-0.3.4.dist-info/entry_points.txt
zdbpydra-0.3.4.dist-info/top_level.txt
zdbpydra-0.3.4.dist-info/RECORD
