Metadata-Version: 2.1
Name: zdbpydra
Version: 0.3.4
Summary: ZDB Hydra API Client
Home-page: https://github.com/herreio/zdbpydra
Author: Donatus Herre
Author-email: donatus.herre@slub-dresden.de
License: GPLv3
License-File: LICENSE
Requires-Dist: requests
